someipy/__init__.py
someipy/client_service_instance.py
someipy/serialization.py
someipy/server_service_instance.py
someipy/service.py
someipy/someipy_logging.py
someipy/someipyd.py
someipy/_internal/__init__.py
someipy/_internal/daemon_client_abcs.py
someipy/_internal/logging.py
someipy/_internal/message_types.py
someipy/_internal/method_result.py
someipy/_internal/return_codes.py
someipy/_internal/session_handler.py
someipy/_internal/simple_timer.py
someipy/_internal/someip_data_processor.py
someipy/_internal/someip_endpoint.py
someipy/_internal/someip_endpoint_factory.py
someipy/_internal/someip_endpoint_storage.py
someipy/_internal/someip_header.py
someipy/_internal/someip_message.py
someipy/_internal/someip_sd_builder.py
someipy/_internal/someip_sd_extractors.py
someipy/_internal/someip_sd_header.py
someipy/_internal/someip_sd_option.py
someipy/_internal/subscribers.py
someipy/_internal/tcp_client_manager.py
someipy/_internal/tcp_connection.py
someipy/_internal/transport_layer_protocol.py
someipy/_internal/utils.py
someipy/_internal/_common/__init__.py
someipy/_internal/_common/endpoint.py
someipy/_internal/_common/event.py
someipy/_internal/_daemon/__init__.py
someipy/_internal/_daemon/daemon_server.py
someipy/_internal/_daemon/daemon_server_client.py
someipy/_internal/_daemon/offer_service_storage.py
someipy/_internal/_daemon/someipy_daemon_client.py
someipy/_internal/_daemon/subscription.py
someipy/_internal/_daemon/subscription_storage.py
someipy/_internal/_daemon/uds_messages.py
someipy/_internal/_sd/__init__.py
someipy/_internal/_sd/sd_message.py
someipy/_internal/_sd/sd_message_creator.py
someipy/_internal/_sd/service_instance.py
someipy/_internal/_sd/deserialization/__init__.py
someipy/_internal/_sd/deserialization/sd_deserialization.py
someipy/_internal/_sd/deserialization/sd_serialization.py
someipy/_internal/_sd/entries/__init__.py
someipy/_internal/_sd/entries/find_service_entry.py
someipy/_internal/_sd/entries/offer_service_entry.py
someipy-2.1.1.dist-info/licenses/LICENSE.md
someipy-2.1.1.dist-info/METADATA
someipy-2.1.1.dist-info/WHEEL
someipy-2.1.1.dist-info/entry_points.txt
someipy-2.1.1.dist-info/top_level.txt
someipy-2.1.1.dist-info/RECORD
