Metadata-Version: 2.4
Name: someipy
Version: 2.1.1
Summary: A Python package implementing the SOME/IP protocol
Home-page: https://github.com/chrizog/someipy
Author: Christian H.
Author-email: someipy.package@gmail.com
Project-URL: Bug Tracker, https://github.com/chrizog/someipy/issues
Project-URL: Repository, https://github.com/chrizog/someipy
Classifier: Intended Audience :: Developers
Classifier: Operating System :: POSIX :: Linux
Classifier: Operating System :: Microsoft :: Windows
Classifier: Programming Language :: Python :: 3.8
Requires-Python: >=3.8
License-File: LICENSE.md
Dynamic: license-file
